odoo/addons/l10n_es_dua/README.rst
odoo/addons/l10n_es_dua/__init__.py
odoo/addons/l10n_es_dua/__manifest__.py
odoo/addons/l10n_es_dua/data/fiscal_position_taxes_dua.xml
odoo/addons/l10n_es_dua/data/fiscal_positions_dua.xml
odoo/addons/l10n_es_dua/data/products_dua.xml
odoo/addons/l10n_es_dua/data/taxes_dua.xml
odoo/addons/l10n_es_dua/i18n/l10n_es_dua.pot
odoo/addons/l10n_es_dua/static/description/icon.png
odoo11_addon_l10n_es_dua-11.0.1.1.0.dist-info/METADATA
odoo11_addon_l10n_es_dua-11.0.1.1.0.dist-info/WHEEL
odoo11_addon_l10n_es_dua-11.0.1.1.0.dist-info/top_level.txt
odoo11_addon_l10n_es_dua-11.0.1.1.0.dist-info/RECORD
